ChebyGCN/__init__.py
ChebyGCN/coarsening.py
ChebyGCN/layers.py
ChebyGCN-0.0.1.dist-info/LICENSE
ChebyGCN-0.0.1.dist-info/METADATA
ChebyGCN-0.0.1.dist-info/WHEEL
ChebyGCN-0.0.1.dist-info/top_level.txt
ChebyGCN-0.0.1.dist-info/RECORD
