Metadata-Version: 2.1
Name: ChebyGCN
Version: 0.0.1
Summary: Implements graph convolution keras layers based on Michaël Defferrard, Xavier Bresson, Pierre Vandergheynst, Convolutional Neural Networks on Graphs with Fast Localized Spectral Filtering, Neural Information Processing Systems (NIPS), 2016.
Home-page: https://github.com/aclyde11/ChebyGCN
Author: Austin Clyde
Author-email: aclyde@uchicago.edu
License: UNKNOWN
Platform: UNKNOWN
Classifier: Programming Language :: Python :: 3
Classifier: Programming Language :: Python :: 2
Classifier: Operating System :: OS Independent
